vmpy/__init__.py
vmpy/__version__.py
vmpy/metrics.py
vmpy/preprocess.py
vmpy/strava.py
vmpy/streams.py
vmpy/utils.py
vmpy-0.1.6.dist-info/DESCRIPTION.rst
vmpy-0.1.6.dist-info/METADATA
vmpy-0.1.6.dist-info/RECORD
vmpy-0.1.6.dist-info/WHEEL
vmpy-0.1.6.dist-info/metadata.json
vmpy-0.1.6.dist-info/top_level.txt
