Metadata-Version: 2.0
Name: vmpy
Version: 0.1.6
Summary: Performance Velo Metrics Toolbox
Home-page: https://github.com/sladkovm/vmpy
Author: Maksym Sladkov
Author-email: sladkovm@gmail.com
License: MIT
Platform: UNKNOWN
Classifier: License :: OSI Approved :: MIT License
Classifier: Programming Language :: Python
Classifier: Programming Language :: Python :: 3.6
Classifier: Operating System :: OS Independent
Classifier: Development Status :: 3 - Alpha
Classifier: Intended Audience :: Developers
Classifier: Intended Audience :: Education
Classifier: Intended Audience :: Healthcare Industry
Classifier: Intended Audience :: Science/Research
Classifier: Topic :: Scientific/Engineering
Requires-Dist: numpy
Requires-Dist: pandas
Requires-Dist: requests
